storage_local/aws_s3_storage_local/AWSStorage.py
storage_local/aws_s3_storage_local/Storage.py
storage_local/aws_s3_storage_local/StorageConstants.py
storage_local/aws_s3_storage_local/StorageDB.py
storage_local/aws_s3_storage_local/StorageInterface.py
storage_local/aws_s3_storage_local/__init__.py
storage_local-0.1.59.dist-info/METADATA
storage_local-0.1.59.dist-info/WHEEL
storage_local-0.1.59.dist-info/top_level.txt
storage_local-0.1.59.dist-info/RECORD
